[{
        "id": 1,
        "salutation": "Mr.",
        "firstName": "Paul",
        "lastName": "Mitchell",
        "addressLine1": "1222 56th St S",
        "addressLine2": "apt 23",
        "city": "Fargo",
        "state": "ND",
        "zipCode": "58104",
        "emailAddress": "ash@sample.com",
        "telePhoneNumber": "5551345699"
    },
    {
        "id": 2,
        "salutation": "Mr.",
        "firstName": "German",
        "lastName": "Mencacci",
        "addressLine1": "1222 56th St S",
        "addressLine2": "apt 23",
        "city": "Fargo",
        "state": "ND",
        "zipCode": "58104",
        "emailAddress": "ash@sample.com",
        "telePhoneNumber": "5551345699"
    }
]